countere_cascadate.v
`include "counter.v"

module countere_cascadate
(input clk, rst, input valid, input fsm_reset, output [3:0] out1, out3, output [2:0] out2, out4);

  	wire en_carry,en_carry2,en_carry3,en3,en4,en_carry4,reset,valid2,valid3,valid4;


    assign reset=rst | fsm_reset;
    //assign valid1=1'b1&valid;

    counter#(.width(4),.MAX(10)) counter_us(.clk(clk),.rst(reset),.en(valid),.count_out(out1),.carry_out(en_carry));

    assign valid2=en_carry&valid;
  
    counter#(.width(3),.MAX(6)) counter_zs(.clk(clk),.rst(reset),.en(valid2),.count_out(out2),.carry_out(en_carry2));
  
  	assign en3=en_carry & en_carry2;
    assign valid3=en3&valid;

    counter#(.width(4),.MAX(10)) counter_um(.clk(clk),.rst(reset),.en(valid3),.count_out(out3),.carry_out(en_carry3));
  
  	assign en4=en_carry&en_carry2&en_carry3;
    assign valid4=en4&valid;

    counter#(.width(3),.MAX(6)) counter_zm(.clk(clk),.rst(reset),.en(valid4),.count_out(out4),.carry_out(en_carry4));

endmodule

fsm.v
`define IDLE 3'b000
`define START 3'b001
`define PAUZA 3'b010
`define STOP 3'b011
`define RESET 3'b100

module fsm //#(parameter ADDR_SIZE=4)
(input clk, input reset, input validare_fsm, input [2:0] optiune, 
//input valid_sw,
output fsm_reset,output valid
//output [ADDR_SIZE-1:0] addr,
//output wr_en,

//output [ADDR_SIZE-1:0] addr2,
//output wr_en2
);

reg [2:0] state_reg,state_next;
reg valid_reg, fsm_reset_reg;
reg valid_next, fsm_reset_next;
reg validare_fsm_reg, validare_fsm_next;

/*reg [ADDR_SIZE-1:0] addr_reg, addr_next;
reg wr_en_reg, wr_en_next;

reg [ADDR_SIZE-1:0] addr2_reg, addr2_next;
reg wr_en2_reg, wr_en2_next;*/

always @(posedge clk or posedge reset) begin
	if(reset) begin
		state_reg <= `RESET;
		valid_reg <= 1'b0;
		fsm_reset_reg <= 1'b0;
		validare_fsm_reg <= 1'b1;
		/*addr_reg <= 0;
		wr_en_reg <= 0;
		addr2_reg <= 0;
		wr_en2_reg <= 0;*/
	end
	else begin
		state_reg <= state_next;
		valid_reg <= valid_next;
		fsm_reset_reg <= fsm_reset_next;
		validare_fsm_reg <= validare_fsm_next;
		/*addr_reg <= addr_next;
		wr_en_reg <= wr_en_next;
		addr2_reg <= addr2_next;
		wr_en2_reg <= wr_en2_next;*/
	end
	
end

always @* begin 
	state_next = state_reg;
	valid_next = valid_reg;
	fsm_reset_next = fsm_reset_reg;
	validare_fsm_next = validare_fsm;
	/*addr_next = addr_reg;
	wr_en_next = wr_en_reg;
	addr2_next = addr2_reg;
	wr_en2_next = wr_en2_reg;*/
	case(state_reg)
	
		`RESET:	begin
			valid_next = 1'b0;
			fsm_reset_next = 1'b0;
			state_next = `IDLE;
		end
		`IDLE: begin
			//wr_en2_next=1'b0;
			if((validare_fsm_reg ^ validare_fsm) & (!validare_fsm)) begin 
			case(optiune)
				`START: state_next = `START;
				`PAUZA: state_next = `PAUZA;
				`STOP: state_next = `STOP;
			endcase
			end
		end
		`START: begin
			valid_next = 1'b1;
			fsm_reset_next = 1'b0;
			/*wr_en_next = 1'b0;
			addr2_next = addr2_reg+1;
			wr_en2_next = 1'b1;*/
			state_next = `IDLE;
		end
		`PAUZA: begin
			//addr_next = addr_reg + 1;
			valid_next = 1'b0;
			fsm_reset_next = 1'b0;
			/*wr_en_next = 1'b1;
			addr2_next = addr2_reg+1;
			wr_en2_next = 1'b1;*/
			state_next = `IDLE;
		end
		`STOP: begin
			valid_next = 1'b0;
			fsm_reset_next = 1'b1;
			/*wr_en_next = 1'b0;
			addr2_next = addr2_reg+1;
			wr_en2_next = 1'b1;*/
			state_next = `IDLE;
		end
	
	endcase
	
	

end

assign fsm_reset=fsm_reset_reg;
assign valid=valid_reg;
/*assign addr=addr_reg;
assign wr_en=wr_en_reg;
assign addr2=addr2_reg;
assign wr_en2=wr_en2_reg;*/
  
endmodule

rom.v

module rom #(parameter DATA_SIZE=3,parameter ADDR_SIZE=4)
(input clk,rst,valid,
input [ADDR_SIZE-1:0] addr, // de la counter
output [DATA_SIZE-1:0] rd_data);

localparam idle = 3'b000 ;
localparam start = 3'b001;
localparam pauza = 3'b010 ;
localparam stop  = 3'b011;

reg [DATA_SIZE-1:0] mem [2**ADDR_SIZE-1:0];
reg [DATA_SIZE-1:0] rd_data_reg, rd_data_next;

always @(posedge clk) begin
    if(rst) begin
        rd_data_reg <= 0;
        mem[0]=idle;
        mem[1]=start;
        mem[2]=pauza;
        mem[3]=idle;
        mem[4]=start;
        mem[5]=stop;
        mem[6]=start;
        mem[7]=pauza;
        mem[8]=stop;
        mem[9]=idle;
        mem[10]=start;
        mem[11]=idle;
        mem[12]=idle;
        mem[13]=stop;
        mem[14]=start;
        mem[15]=pauza;
    end
    else begin
        rd_data_reg <= rd_data_next;
    end
end

always @* begin
    rd_data_next = rd_data_reg;
    if(valid)
        rd_data_next = mem[addr];
end
assign rd_data = rd_data_reg;
endmodule

counter.v
module counter#(parameter width = 4,
                parameter MAX = 10)
  			   (input clk,input rst,input en,output carry_out, output [width-1:0] count_out);

  reg [width-1:0] count_ff,count_next;
  reg carry_ff, carry_next;
  // this always bloc will be synthesize as combinational logic
  assign count_out=count_ff;
  assign carry_out=carry_ff;
  always @* begin
    count_next = count_ff;
    carry_next = carry_ff; 
    if(en) begin
      if(count_ff == (MAX-2)) begin
        carry_next='b1;
      end
      if(count_ff == (MAX-1)) begin
	carry_next='b0;
        count_next = 'b0;
      end else begin
        count_next = count_ff+1'b1;
      end
    end
  end
  
  // this always bloc will be synthesize as sequential logic
  always @(posedge clk or posedge rst) begin
    if(rst) begin
      count_ff <= 'b0;
      carry_ff<='b0;

  // if you don`t know the width use 'b0 and the compiler will insert 0 on all defined bits
    end else begin
      count_ff <= count_next;
      carry_ff <= carry_next;
    end
  end
endmodule

clk_div.v
module clk_div#(parameter width = 4,
                parameter MAX = 10)
  			   (input clk,input rst,input en, output div_clk);
  
  localparam HALD_COUNT = (MAX-1)/2;
  reg [width-1:0] count_ff,count_next;
  reg drive_ff, drive_next;
  
  assign div_clk = drive_ff;
  
  
  always @* begin
    drive_next = drive_ff;
    count_next = count_ff;
    if(en) begin
      if(count_ff == (MAX-1)) begin
        drive_next = 1'b0;
        count_next = 'b0;
      end else begin
        count_next = count_ff+1'b1;
        if(count_ff < HALD_COUNT) begin
          drive_next = 1'b0;
        end else begin
          drive_next = 1'b1;
        end
      end
    end
  end
  

  always @(posedge clk or posedge rst) begin
    if(rst) begin
      drive_ff <= 1'b0;
      count_ff <= 'b0;  
    end else begin
      drive_ff <= drive_next;
      count_ff <= count_next;
    end
  end
endmodule

countere_fsm_top.v
`timescale 1ns / 1ps
`include "countere_cascadate.v"
`include "fsm.v"

module countere_top(input clk,rst,input [2:0] optiune_user, input validare_fsm, input switch,
//output [3:0] out1, out3, output [2:0] out2, out4,
//output [3:0] outt1, outt3, output [2:0] outt2, outt4,
//output [13:0] rez,
//output [3:0] addr,
//output wr_en,
//output [3:0] addr2,
//output wr_en2,
//output [2:0] rez2
output valid, fsm_reset,
output [2:0] optiune
);

//wire [3:0] address,address2;

wire [2:0] optiune_rom;
wire validare_final;
wire valid_clk;
wire [3:0] addr;

clk_div #(.width(19),.MAX(500000)) divizor2_50MHz_100Hz(.clk(clk),.rst(rst),.en(1'b1),.div_clk(valid_clk));

counter#(.width(4),.MAX(15)) counter_rom(.clk(valid_clk),.rst(rst),.en(switch),.count_out(addr),.carry_out(carry_out));

rom #(.DATA_SIZE(3), .ADDR_SIZE(4)) rom1(.clk(clk),.rst(rst),.valid(switch),.addr(addr),.rd_data(optiune_rom));

assign optiune = switch ? optiune_rom : optiune_user;

assign validare_final = switch ? valid_clk : validare_fsm;

fsm fsm1(.clk(valid_clk),.reset(rst),.validare_fsm(validare_final),.optiune(optiune),.valid(valid),.fsm_reset(fsm_reset));

//wire valid_c,fsm_reset_c;

//assign valid_c=valid;
//assign fsm_reset_c=fsm_reset;

//countere_cascadate countere(.clk(clk), .rst(rst), .valid(valid_c), .fsm_reset(fsm_reset_c),.out1(outt1),.out2(outt2),.out3(outt3),.out4(outt4));

//sram #(.ADDR_SIZE(4), .DATA_SIZE(14)) sram1(.clk(clk),.wr_en(wr_en),.addr(addr), .wr_data({outt1,outt2,outt3,outt4}), .rd_data(rez));
//sram #(.ADDR_SIZE(4), .DATA_SIZE(3)) sram2(.clk(clk),.wr_en(wr_en2),.addr(addr2),.wr_data(optiune),.rd_data(rez2));


endmodule

fsm_rom_tb.v
//`include "countere_fsm_top.v"
`timescale 1ns / 1ps

module fsm_rom_tb();
reg rst,clk;
reg validare_fsm;
reg [2:0]optiune_user;
reg switch;
wire valid;
wire fsm_reset;
wire [2:0] optiune;


countere_top top2(.clk(clk), .rst(rst),.optiune_user(optiune_user),.validare_fsm(validare_fsm),.switch(switch)
,.valid(valid),.fsm_reset(fsm_reset),.optiune(optiune));

initial begin
clk = 1'b0;

forever #1 clk = !clk;
end

initial begin

    rst = 1'b1;
    validare_fsm = 1'b1;
    //validare_rom = 1'b1;
    optiune_user = 3'b000;
    switch = 0;
  	
  //#2000; 2000ns
  	//repeat(1000) @(posedge clk); 
  	#100
    rst = 1'b0;
    #1000;

    optiune_user = 3'b001;
    //#2000;
  repeat(1000) @(posedge clk); 
    validare_fsm = 1'b0;
    #2000;
    validare_fsm = 1'b1;
    #1000;

    //rst = 1'b1;

    optiune_user = 3'b000;
    //#2000;
  repeat(1000) @(posedge clk); 
    validare_fsm = 1'b0;
    #2000;
    validare_fsm = 1'b1;
    #1000;
    
  	optiune_user = 3'b011;
    //#1000;
  repeat(100) @(posedge clk); 
  	optiune_user = 3'b100;
  //#1000;
  repeat(1000) @(posedge clk); 
  	optiune_user = 3'b110;
  //#1000;
  repeat(1000) @(posedge clk); 
  	optiune_user = 3'b010;
  //#1000;
  repeat(1000) @(posedge clk); 
  
  	optiune_user = 3'b000;
  //#2000;
  repeat(1000) @(posedge clk); 
    validare_fsm = 1'b0;
    #2000;
    validare_fsm = 1'b1; 
    #1000;

    optiune_user = 3'b010;
    //#2000;
  repeat(100) @(posedge clk); 
    validare_fsm = 1'b0;
   	#2000;
    validare_fsm = 1'b1;
    #1000;
  
  	optiune_user = 3'b000;
  //#1000;
  repeat(1000) @(posedge clk); 
    optiune_user = 3'b011;
    #2000;
    validare_fsm = 1'b0;
    #2000;
    validare_fsm = 1'b1;
  //#1000;
  repeat(1000) @(posedge clk); 


  switch = 1'b1;
  //validare_rom = 1'b0;
  #100;
  repeat(10000) @(posedge clk);
  
$finish();
end
  
  initial begin
    $dumpfile("dump.vcd"); 
    $dumpvars;
  end
endmodule

dump.vcd
$date
	Wed Jan 10 19:18:20 2024
$end
$version
	ModelSim Version 10.5b
$end
$timescale
	1ps
$end

$scope module fsm_rom_tb $end
$var reg 1 ! rst $end
$var reg 1 " clk $end
$var reg 1 # validare_fsm $end
$var reg 3 $ optiune_user [2:0] $end
$var reg 1 % switch $end
$var wire 1 & valid $end
$var wire 1 ' fsm_reset $end
$var wire 1 ( optiune [2] $end
$var wire 1 ) optiune [1] $end
$var wire 1 * optiune [0] $end

$scope module top2 $end
$var wire 1 + clk $end
$var wire 1 , rst $end
$var wire 1 - optiune_user [2] $end
$var wire 1 . optiune_user [1] $end
$var wire 1 / optiune_user [0] $end
$var wire 1 0 validare_fsm $end
$var wire 1 1 switch $end
$var wire 1 & valid $end
$var wire 1 ' fsm_reset $end
$var wire 1 ( optiune [2] $end
$var wire 1 ) optiune [1] $end
$var wire 1 * optiune [0] $end
$var wire 1 2 optiune_rom [2] $end
$var wire 1 3 optiune_rom [1] $end
$var wire 1 4 optiune_rom [0] $end
$var wire 1 5 validare_final $end
$var wire 1 6 valid_clk $end
$var wire 1 7 addr [3] $end
$var wire 1 8 addr [2] $end
$var wire 1 9 addr [1] $end
$var wire 1 : addr [0] $end
$var wire 1 ; carry_out $end

$scope module divizor2_50MHz_100Hz $end
$var parameter 32 < width $end
$var parameter 32 = MAX $end
$var parameter 32 > HALD_COUNT $end
$var wire 1 + clk $end
$var wire 1 , rst $end
$var wire 1 ? en $end
$var wire 1 6 div_clk $end
$var reg 19 @ count_ff [18:0] $end
$var reg 19 A count_next [18:0] $end
$var reg 1 B drive_ff $end
$var reg 1 C drive_next $end
$upscope $end

$scope module counter_rom $end
$var parameter 32 D width $end
$var parameter 32 E MAX $end
$var wire 1 6 clk $end
$var wire 1 , rst $end
$var wire 1 1 en $end
$var wire 1 ; carry_out $end
$var wire 1 7 count_out [3] $end
$var wire 1 8 count_out [2] $end
$var wire 1 9 count_out [1] $end
$var wire 1 : count_out [0] $end
$var reg 4 F count_ff [3:0] $end
$var reg 4 G count_next [3:0] $end
$var reg 1 H carry_ff $end
$var reg 1 I carry_next $end
$upscope $end

$scope module rom1 $end
$var parameter 32 J DATA_SIZE $end
$var parameter 32 K ADDR_SIZE $end
$var parameter 3 L idle $end
$var parameter 3 M start $end
$var parameter 3 N pauza $end
$var parameter 3 O stop $end
$var wire 1 + clk $end
$var wire 1 , rst $end
$var wire 1 1 valid $end
$var wire 1 7 addr [3] $end
$var wire 1 8 addr [2] $end
$var wire 1 9 addr [1] $end
$var wire 1 : addr [0] $end
$var wire 1 2 rd_data [2] $end
$var wire 1 3 rd_data [1] $end
$var wire 1 4 rd_data [0] $end
$var reg 3 P rd_data_reg [2:0] $end
$var reg 3 Q rd_data_next [2:0] $end
$upscope $end

$scope module fsm1 $end
$var wire 1 6 clk $end
$var wire 1 , reset $end
$var wire 1 5 validare_fsm $end
$var wire 1 ( optiune [2] $end
$var wire 1 ) optiune [1] $end
$var wire 1 * optiune [0] $end
$var wire 1 ' fsm_reset $end
$var wire 1 & valid $end
$var reg 3 R state_reg [2:0] $end
$var reg 3 S state_next [2:0] $end
$var reg 1 T valid_reg $end
$var reg 1 U fsm_reset_reg $end
$var reg 1 V valid_next $end
$var reg 1 W fsm_reset_next $end
$var reg 1 X validare_fsm_reg $end
$var reg 1 Y validare_fsm_next $end
$upscope $end
$upscope $end
$upscope $end
$enddefinitions $end
#0
$dumpvars
1!
0"
1#
b0 $
0%
b0 @
b1 A
0B
0C
b0 F
b0 G
0H
0I
bx P
bx Q
b100 R
b0 S
0T
0U
0V
0W
1X
1Y
b10011 <
b1111010000100100000 =
b111101000010001111 >
b100 D
b1111 E
b11 J
b100 K
b0 L
b1 M
b10 N
b11 O
0&
0'
0*
0)
0(
x4
x3
x2
15
06
0:
09
08
07
0;
01
10
0/
0.
0-
1,
0+
1?
$end
#1000
1"
1+
b0 P
04
03
02
b0 Q
#2000
0"
0+
#3000
1"
1+
#4000
0"
0+
#5000
1"
1+
#6000
0"
0+
#7000
1"
1+
#8000
0"
0+
#9000
1"
1+
#10000
0"
0+
#11000
1"
1+
#12000
0"
0+
#13000
1"
1+
#14000
0"
0+
#15000
1"
1+
#16000
0"
0+
#17000
1"
1+
#18000
0"
0+
#19000
1"
1+
#20000
0"
0+
#21000
1"
1+
#22000
0"
0+
#23000
1"
1+
#24000
0"
0+
#25000
1"
1+
#26000
0"
0+
#27000
1"
1+
#28000
0"
0+
#29000
1"
1+
#30000
0"
0+
#31000
1"
1+
#32000
0"
0+
#33000
1"
1+
#34000
0"
0+
#35000
1"
1+
#36000
0"
0+
#37000
1"
1+
#38000
0"
0+
#39000
1"
1+
#40000
0"
0+
#41000
1"
1+
#42000
0"
0+
#43000
1"
1+
#44000
0"
0+
#45000
1"
1+
#46000
0"
0+
#47000
1"
1+
#48000
0"
0+
#49000
1"
1+
#50000
0"
0+
#51000
1"
1+
#52000
0"
0+
#53000
1"
1+
#54000
0"
0+
#55000
1"
1+
#56000
0"
0+
#57000
1"
1+
#58000
0"
0+
#59000
1"
1+
#60000
0"
0+
#61000
1"
1+
#62000
0"
0+
#63000
1"
1+
#64000
0"
0+
#65000
1"
1+
#66000
0"
0+
#67000
1"
1+
#68000
0"
0+
#69000
1"
1+
#70000
0"
0+
#71000
1"
1+
#72000
0"
0+
#73000
1"
1+
#74000
0"
0+
#75000
1"
1+
#76000
0"
0+
#77000
1"
1+
#78000
0"
0+
#79000
1"
1+
#80000
0"
0+
#81000
1"
1+
#82000
0"
0+
#83000
1"
1+
#84000
0"
0+
#85000
1"
1+
#86000
0"
0+
#87000
1"
1+
#88000
0"
0+
#89000
1"
1+
#90000
0"
0+
#91000
1"
1+
#92000
0"
0+
#93000
1"
1+
#94000
0"
0+
#95000
1"
1+
#96000
0"
0+
#97000
1"
1+
#98000
0"
0+
#99000
1"
1+
#100000
0!
0"
0,
0+
#101000
1"
1+
b1 @
b10 A
#102000
0"
0+
#103000
1"
1+
b10 @
b11 A
#104000
0"
0+
#105000
1"
1+
b11 @
b100 A
#106000
0"
0+
#107000
1"
1+
b100 @
b101 A
#108000
0"
0+
#109000
1"
1+
b101 @
b110 A
#110000
0"
0+
#111000
1"
1+
b110 @
b111 A
#112000
0"
0+
#113000
1"
1+
b111 @
b1000 A
#114000
0"
0+
#115000
1"
1+
b1000 @
b1001 A
#116000
0"
0+
#117000
1"
1+
b1001 @
b1010 A
#118000
0"
0+
#119000
1"
1+
b1010 @
b1011 A
#120000
0"
0+
#121000
1"
1+
b1011 @
b1100 A
#122000
0"
0+
#123000
1"
1+
b1100 @
b1101 A
#124000
0"
0+
#125000
1"
1+
b1101 @
b1110 A
#126000
0"
0+
#127000
1"
1+
b1110 @
b1111 A
#128000
0"
0+
#129000
1"
1+
b1111 @
b10000 A
#130000
0"
0+
#131000
1"
1+
b10000 @
b10001 A
#132000
0"
0+
#133000
1"
1+
b10001 @
b10010 A
#134000
0"
0+
#135000
1"
1+
b10010 @
b10011 A
#136000
0"
0+
#137000
1"
1+
b10011 @
b10100 A
#138000
0"
0+
#139000
1"
1+
b10100 @
b10101 A
#140000
0"
0+
#141000
1"
1+
b10101 @
b10110 A
#142000
0"
0+
#143000
1"
1+
b10110 @
b10111 A
#144000
0"
0+
#145000
1"
1+
b10111 @
b11000 A
#146000
0"
0+
#147000
1"
1+
b11000 @
b11001 A
#148000
0"
0+
#149000
1"
1+
b11001 @
b11010 A
#150000
0"
0+
#151000
1"
1+
b11010 @
b11011 A
#152000
0"
0+
#153000
1"
1+
b11011 @
b11100 A
#154000
0"
0+
#155000
1"
1+
b11100 @
b11101 A
#156000
0"
0+
#157000
1"
1+
b11101 @
b11110 A
#158000
0"
0+
#159000
1"
1+
b11110 @
b11111 A
#160000
0"
0+
#161000
1"
1+
b11111 @
b100000 A
#162000
0"
0+
#163000
1"
1+
b100000 @
b100001 A
#164000
0"
0+
#165000
1"
1+
b100001 @
b100010 A
#166000
0"
0+
#167000
1"
1+
b100010 @
b100011 A
#168000
0"
0+
#169000
1"
1+
b100011 @
b100100 A
#170000
0"
0+
#171000
1"
1+
b100100 @
b100101 A
#172000
0"
0+
#173000
1"
1+
b100101 @
b100110 A
#174000
0"
0+
#175000
1"
1+
b100110 @
b100111 A
#176000
0"
0+
#177000
1"
1+
b100111 @
b101000 A
#178000
0"
0+
#179000
1"
1+
b101000 @
b101001 A
#180000
0"
0+
#181000
1"
1+
b101001 @
b101010 A
#182000
0"
0+
#183000
1"
1+
b101010 @
b101011 A
#184000
0"
0+
#185000
1"
1+
b101011 @
b101100 A
#186000
0"
0+
#187000
1"
1+
b101100 @
b101101 A
#188000
0"
0+
#189000
1"
1+
b101101 @
b101110 A
#190000
0"
0+
#191000
1"
1+
b101110 @
b101111 A
#192000
0"
0+
#193000
1"
1+
b101111 @
b110000 A
#194000
0"
0+
#195000
1"
1+
b110000 @
b110001 A
#196000
0"
0+
#197000
1"
1+
b110001 @
b110010 A
#198000
0"
0+
#199000
1"
1+
b110010 @
b110011 A
#200000
0"
0+
#201000
1"
1+
b110011 @
b110100 A
#202000
0"
0+
#203000
1"
1+
b110100 @
b110101 A
#204000
0"
0+
#205000
1"
1+
b110101 @
b110110 A
#206000
0"
0+
#207000
1"
1+
b110110 @
b110111 A
#208000
0"
0+
#209000
1"
1+
b110111 @
b111000 A
#210000
0"
0+
#211000
1"
1+
b111000 @
b111001 A
#212000
0"
0+
#213000
1"
1+
b111001 @
b111010 A
#214000
0"
0+
#215000
1"
1+
b111010 @
b111011 A
#216000
0"
0+
#217000
1"
1+
b111011 @
b111100 A
#218000
0"
0+
#219000
1"
1+
b111100 @
b111101 A
#220000
0"
0+
#221000
1"
1+
b111101 @
b111110 A
#222000
0"
0+
#223000
1"
1+
b111110 @
b111111 A
#224000
0"
0+
#225000
1"
1+
b111111 @
b1000000 A
#226000
0"
0+
#227000
1"
1+
b1000000 @
b1000001 A
#228000
0"
0+
#229000
1"
1+
b1000001 @
b1000010 A
#230000
0"
0+
#231000
1"
1+
b1000010 @
b1000011 A
#232000
0"
0+
#233000
1"
1+
b1000011 @
b1000100 A
#234000
0"
0+
#235000
1"
1+
b1000100 @
b1000101 A
#236000
0"
0+
#237000
1"
1+
b1000101 @
b1000110 A
#238000
0"
0+
#239000
1"
1+
b1000110 @
b1000111 A
#240000
0"
0+
#241000
1"
1+
b1000111 @
b1001000 A
#242000
0"
0+
#243000
1"
1+
b1001000 @
b1001001 A
#244000
0"
0+
#245000
1"
1+
b1001001 @
b1001010 A
#246000
0"
0+
#247000
1"
1+
b1001010 @
b1001011 A
#248000
0"
0+
#249000
1"
1+
b1001011 @
b1001100 A
#250000
0"
0+
#251000
1"
1+
b1001100 @
b1001101 A
#252000
0"
0+
#253000
1"
1+
b1001101 @
b1001110 A
#254000
0"
0+
#255000
1"
1+
b1001110 @
b1001111 A
#256000
0"
0+
#257000
1"
1+
b1001111 @
b1010000 A
#258000
0"
0+
#259000
1"
1+
b1010000 @
b1010001 A
#260000
0"
0+
#261000
1"
1+
b1010001 @
b1010010 A
#262000
0"
0+
#263000
1"
1+
b1010010 @
b1010011 A
#264000
0"
0+
#265000
1"
1+
b1010011 @
b1010100 A
#266000
0"
0+
#267000
1"
1+
b1010100 @
b1010101 A
#268000
0"
0+
#269000
1"
1+
b1010101 @
b1010110 A
#270000
0"
0+
#271000
1"
1+
b1010110 @
b1010111 A
#272000
0"
0+
#273000
1"
1+
b1010111 @
b1011000 A
#274000
0"
0+
#275000
1"
1+
b1011000 @
b1011001 A
#276000
0"
0+
#277000
1"
1+
b1011001 @
b1011010 A
#278000
0"
0+
#279000
1"
1+
b1011010 @
b1011011 A
#280000
0"
0+
#281000
1"
1+
b1011011 @
b1011100 A
#282000
0"
0+
#283000
1"
1+
b1011100 @
b1011101 A
#284000
0"
0+
#285000
1"
1+
b1011101 @
b1011110 A
#286000
0"
0+
#287000
1"
1+
b1011110 @
b1011111 A
#288000
0"
0+
#289000
1"
1+
b1011111 @
b1100000 A
#290000
0"
0+
#291000
1"
1+
b1100000 @
b1100001 A
#292000
0"
0+
#293000
1"
1+
b1100001 @
b1100010 A
#294000
0"
0+
#295000
1"
1+
b1100010 @
b1100011 A
#296000
0"
0+
#297000
1"
1+
b1100011 @
b1100100 A
#298000
0"
0+
#299000
1"
1+
b1100100 @
b1100101 A
#300000
0"
0+
#301000
1"
1+
b1100101 @
b1100110 A
#302000
0"
0+
#303000
1"
1+
b1100110 @
b1100111 A
#304000
0"
0+
#305000
1"
1+
b1100111 @
b1101000 A
#306000
0"
0+
#307000
1"
1+
b1101000 @
b1101001 A
#308000
0"
0+
#309000
1"
1+
b1101001 @
b1101010 A
#310000
0"
0+
#311000
1"
1+
b1101010 @
b1101011 A
#312000
0"
0+
#313000
1"
1+
b1101011 @
b1101100 A
#314000
0"
0+
#315000
1"
1+
b1101100 @
b1101101 A
#316000
0"
0+
#317000
1"
1+
b1101101 @
b1101110 A
#318000
0"
0+
#319000
1"
1+
b1101110 @
b1101111 A
#320000
0"
0+
#321000
1"
1+
b1101111 @
b1110000 A
#322000
0"
0+
#323000
1"
1+
b1110000 @
b1110001 A
#324000
0"
0+
#325000
1"
1+
b1110001 @
b1110010 A
#326000
0"
0+
#327000
1"
1+
b1110010 @
b1110011 A
#328000
0"
0+
#329000
1"
1+
b1110011 @
b1110100 A
#330000
0"
0+
#331000
1"
1+
b1110100 @
b1110101 A
#332000
0"
0+
#333000
1"
1+
b1110101 @
b1110110 A
#334000
0"
0+
#335000
1"
1+
b1110110 @
b1110111 A
#336000
0"
0+
#337000
1"
1+
b1110111 @
b1111000 A
#338000
0"
0+
#339000
1"
1+
b1111000 @
b1111001 A
#340000
0"
0+
#341000
1"
1+
b1111001 @
b1111010 A
#342000
0"
0+
#343000
1"
1+
b1111010 @
b1111011 A
#344000
0"
0+
#345000
1"
1+
b1111011 @
b1111100 A
#346000
0"
0+
#347000
1"
1+
b1111100 @
b1111101 A
#348000
0"
0+
#349000
1"
1+
b1111101 @
b1111110 A
#350000
0"
0+
#351000
1"
1+
b1111110 @
b1111111 A
#352000
0"
0+
#353000
1"
1+
b1111111 @
b10000000 A
#354000
0"
0+
#355000
1"
1+
b10000000 @
b10000001 A
#356000
0"
0+
#357000
1"
1+
b10000001 @
b10000010 A
#358000
0"
0+
#359000
1"
1+
b10000010 @
b10000011 A
#360000
0"
0+
#361000
1"
1+
b10000011 @
b10000100 A
#362000
0"
0+
#363000
1"
1+
b10000100 @
b10000101 A
#364000
0"
0+
#365000
1"
1+
b10000101 @
b10000110 A
#366000
0"
0+
#367000
1"
1+
b10000110 @
b10000111 A
#368000
0"
0+
#369000
1"
1+
b10000111 @
b10001000 A
#370000
0"
0+
#371000
1"
1+
b10001000 @
b10001001 A
#372000
0"
0+
#373000
1"
1+
b10001001 @
b10001010 A
#374000
0"
0+
#375000
1"
1+
b10001010 @
b10001011 A
#376000
0"
0+
#377000
1"
1+
b10001011 @
b10001100 A
#378000
0"
0+
#379000
1"
1+
b10001100 @
b10001101 A
#380000
0"
0+
#381000
1"
1+
b10001101 @
b10001110 A
#382000
0"
0+
#383000
1"
1+
b10001110 @
b10001111 A
#384000
0"
0+
#385000
1"
1+
b10001111 @
b10010000 A
#386000
0"
0+
#387000
1"
1+
b10010000 @
b10010001 A
#388000
0"
0+
#389000
1"
1+
b10010001 @
b10010010 A
#390000
0"
0+
#391000
1"
1+
b10010010 @
b10010011 A
#392000
0"
0+
#393000
1"
1+
b10010011 @
b10010100 A
#394000
0"
0+
#395000
1"
1+
b10010100 @
b10010101 A
#396000
0"
0+
#397000
1"
1+
b10010101 @
b10010110 A
#398000
0"
0+
#399000
1"
1+
b10010110 @
b10010111 A
#400000
0"
0+
#401000
1"
1+
b10010111 @
b10011000 A
#402000
0"
0+
#403000
1"
1+
b10011000 @
b10011001 A
#404000
0"
0+
#405000
1"
1+
b10011001 @
b10011010 A
#406000
0"
0+
#407000
1"
1+
b10011010 @
b10011011 A
#408000
0"
0+
#409000
1"
1+
b10011011 @
b10011100 A
#410000
0"
0+
#411000
1"
1+
b10011100 @
b10011101 A
#412000
0"
0+
#413000
1"
1+
b10011101 @
b10011110 A
#414000
0"
0+
#415000
1"
1+
b10011110 @
b10011111 A
#416000
0"
0+
#417000
1"
1+
b10011111 @
b10100000 A
#418000
0"
0+
#419000
1"
1+
b10100000 @
b10100001 A
#420000
0"
0+
#421000
1"
1+
b10100001 @
b10100010 A
#422000
0"
0+
#423000
1"
1+
b10100010 @
b10100011 A
#424000
0"
0+
#425000
1"
1+
b10100011 @
b10100100 A
#426000
0"
0+
#427000
1"
1+
b10100100 @
b10100101 A
#428000
0"
0+
#429000
1"
1+
b10100101 @
b10100110 A
#430000
0"
0+
#431000
1"
1+
b10100110 @
b10100111 A
#432000
0"
0+
#433000
1"
1+
b10100111 @
b10101000 A
#434000
0"
0+
#435000
1"
1+
b10101000 @
b10101001 A
#436000
0"
0+
#437000
1"
1+
b10101001 @
b10101010 A
#438000
0"
0+
#439000
1"
1+
b10101010 @
b10101011 A
#440000
0"
0+
#441000
1"
1+
b10101011 @
b10101100 A
#442000
0"
0+
#443000
1"
1+
b10101100 @
b10101101 A
#444000
0"
0+
#445000
1"
1+
b10101101 @
b10101110 A
#446000
0"
0+
#447000
1"
1+
b10101110 @
b10101111 A
#448000
0"
0+
#449000
1"
1+
b10101111 @
b10110000 A
#450000
0"
0+
#451000
1"
1+
b10110000 @
b10110001 A
#452000
0"
0+
#453000
1"
1+
b10110001 @
b10110010 A
#454000
0"
0+
#455000
1"
1+
b10110010 @
b10110011 A
#456000
0"
0+
#457000
1"
1+
b10110011 @
b10110100 A
#458000
0"
0+
#459000
1"
1+
b10110100 @
b10110101 A
#460000
0"
0+
#461000
1"
1+
b10110101 @
b10110110 A
#462000
0"
0+
#463000
1"
1+
b10110110 @
b10110111 A
#464000
0"
0+
#465000
1"
1+
b10110111 @
b10111000 A
#466000
0"
0+
#467000
1"
1+
b10111000 @
b10111001 A
#468000
0"
0+
#469000
1"
1+
b10111001 @
b10111010 A
#470000
0"
0+
#471000
1"
1+
b10111010 @
b10111011 A
#472000
0"
0+
#473000
1"
1+
b10111011 @
b10111100 A
#474000
0"
0+
#475000
1"
1+
b10111100 @
b10111101 A
#476000
0"
0+
#477000
1"
1+
b10111101 @
b10111110 A
#478000
0"
0+
#479000
1"
1+
b10111110 @
b10111111 A
#480000
0"
0+
#481000
1"
1+
b10111111 @
b11000000 A
#482000
0"
0+
#483000
1"
1+
b11000000 @
b11000001 A
#484000
0"
0+
#485000
1"
1+
b11000001 @
b11000010 A
#486000
0"
0+
#487000
1"
1+
b11000010 @
b11000011 A
#488000
0"
0+
#489000
1"
1+
b11000011 @
b11000100 A
#490000
0"
0+
#491000
1"
1+
b11000100 @
b11000101 A
#492000
0"
0+
#493000
1"
1+
b11000101 @
b11000110 A
#494000
0"
0+
#495000
1"
1+
b11000110 @
b11000111 A
#496000
0"
0+
#497000
1"
1+
b11000111 @
b11001000 A
#498000
0"
0+
